LICENSE.txt
MANIFEST.in
README.rst
setup.cfg
setup.py
jagged/__init__.py
jagged/base.py
jagged/bcolz_backend.py
jagged/blosc_backend.py
jagged/bloscpack_backend.py
jagged/h5py_backend.py
jagged/joblib_backend.py
jagged/misc.py
jagged/mmap_backend.py
jagged/npy_backend.py
jagged/pickle_backend.py
jagged.egg-info/PKG-INFO
jagged.egg-info/SOURCES.txt
jagged.egg-info/dependency_links.txt
jagged.egg-info/requires.txt
jagged.egg-info/top_level.txt
jagged/benchmarks/__init__.py
jagged/benchmarks/utils.py
jagged/compression/__init__.py
jagged/compression/compressors.py
jagged/tests/__init__.py
jagged/tests/fixtures.py
jagged/tests/test_raw_stores.py