Metadata-Version: 1.1
Name: jagged
Version: 0.1.0
Summary: Simple tricks for efficient loading or merging collections of unevenly sized elements
Home-page: https://github.com/sdvillal/jagged
Author: Santi Villalba
Author-email: sdvillal@gmail.com
License: BSD 3 clause
Platform: UNKNOWN
Classifier: Intended Audience :: Science/Research
Classifier: Intended Audience :: Developers
Classifier: Topic :: Software Development
Classifier: Topic :: Scientific/Engineering
Classifier: License :: OSI Approved
Classifier: Programming Language :: Python :: 2
Classifier: Programming Language :: Python :: 2.7
Classifier: Programming Language :: Python :: 3
Classifier: Programming Language :: Python :: 3.4
Classifier: Operating System :: Unix
